markdown2anki/__init__.py
markdown2anki/logger.py
markdown2anki/output_handler.py
markdown2anki/template for coding cards.md
markdown2anki/version_check.py
markdown2anki/config/Markdown2Anki.apkg
markdown2anki/config/configs_handle.py
markdown2anki/config/first_config.py
markdown2anki/config/parse_args.py
markdown2anki/config/welcome_message.txt
markdown2anki/config/config_setup/__init__.py
markdown2anki/config/config_setup/casters.py
markdown2anki/config/config_setup/validators.py
markdown2anki/md_2_anki/__init__.py
markdown2anki/md_2_anki/process_card/__init__.py
markdown2anki/md_2_anki/process_card/compile/__init__.py
markdown2anki/md_2_anki/process_card/compile/custom_plugins/obsidian_image_plugin.py
markdown2anki/md_2_anki/process_card/compile/custom_plugins/obsidian_link_plugin.py
markdown2anki/md_2_anki/process_card/extract/__init__.py
markdown2anki/md_2_anki/process_card/format/formatters.py
markdown2anki/md_2_anki/process_card/format/wrappers.py
markdown2anki/md_2_anki/process_card/swap/__init__.py
markdown2anki/md_2_anki/process_clozes/__init__.py
markdown2anki/md_2_anki/process_images/__init__.py
markdown2anki/md_2_anki/utils/__init__.py
markdown2anki/md_2_anki/utils/card_error.py
markdown2anki/md_2_anki/utils/card_types.py
markdown2anki/md_2_anki/utils/common_types.py
markdown2anki/md_2_anki/utils/debug_tools.py
markdown2anki/utils/common_types.py
markdown2anki/utils/debug_tools.py
markdown2anki-0.2.0.dist-info/LICENSES
markdown2anki-0.2.0.dist-info/METADATA
markdown2anki-0.2.0.dist-info/WHEEL
markdown2anki-0.2.0.dist-info/entry_points.txt
markdown2anki-0.2.0.dist-info/top_level.txt
markdown2anki-0.2.0.dist-info/RECORD
