Metadata-Version: 2.1
Name: markdown2anki
Version: 0.2.0
Summary: A CLI tool and an apkg template to allow you to create flashcards from markdown and have a better experience while using anki for your studies. 🌸
Author-email: "Alex Biosa (mochitto)" <mochittodeveloper@gmail.com>
License: Copyright (C) 2023, Alex Biosa (mochitto), mochittodeveloper@gmail.com 
Project-URL: documentation, https://github.com/Mochitto/Markdown2Anki/blob/master/README.md
Project-URL: repository, https://github.com/Mochitto/Markdown2Anki
Project-URL: changelog, https://github.com/Mochitto/Markdown2Anki/blob/master/CHANGELOG.md
Keywords: anki,flashcard,markdown,apkg,cli
Classifier: Development Status :: 4 - Beta
Classifier: Environment :: Console
Classifier: Framework :: Pytest
Classifier: Intended Audience :: Education
Classifier: Intended Audience :: End Users/Desktop
Classifier: License :: OSI Approved :: GNU General Public License v3 (GPLv3)
Classifier: Operating System :: OS Independent
Classifier: Topic :: Education
Classifier: Typing :: Typed
Requires-Python: >=3.10
License-File: LICENSES
Requires-Dist: mistune (==2.0.4)
Requires-Dist: Pygments (==2.13.0)
Requires-Dist: type-config (==1.3.0)
Requires-Dist: requests (==2.28.2)
Provides-Extra: dev
Requires-Dist: pytest ; extra == 'dev'
Requires-Dist: black ; extra == 'dev'
